agent_sdk/__init__.py
agent_sdk/agent.py
agent_sdk/bridge.py
agent_sdk/decorators.py
agent_sdk/events.py
agent_sdk/runner.py
agent_sdk/sandbox.py
agent_sdk/swarm.py
agent_sdk/tools.py
agent_sdk/utils.py
agent_sdk/clients/__init__.py
agent_sdk/clients/anthropic.py
agent_sdk/clients/base.py
agent_sdk/clients/gemini.py
agent_sdk/clients/ollama.py
agent_sdk/clients/openai.py
agent_sdk/clients/openrouter.py
agent_sdk/middleware/__init__.py
agent_sdk/middleware/approval.py
agent_sdk/middleware/base.py
agent_sdk/middleware/context.py
agent_sdk/middleware/logger.py
agent_sdk/middleware/memory.py
agent_sdk/middleware/memory_manager.py
agent_sdk/middleware/rag.py
agent_sdk/middleware/reflection.py
agent_sdk/middleware/storage.py
agent_sdk_core-0.1.6.dist-info/licenses/LICENSE
agent_sdk_core-0.1.6.dist-info/METADATA
agent_sdk_core-0.1.6.dist-info/WHEEL
agent_sdk_core-0.1.6.dist-info/top_level.txt
agent_sdk_core-0.1.6.dist-info/RECORD
