Metadata-Version: 2.4
Name: agent-sdk-core
Version: 0.1.6
Summary: A lightweight, zero-dependency focused AI Agent Framework for Python.
Author-email: Halibo01 <halilsan1994@hotmail.com>
License: MIT
Project-URL: Homepage, https://docs.agent-sdk-core.dev
Project-URL: Repository, https://github.com/Halibo01/agent_sdk.git
Project-URL: Issues, https://github.com/Halibo01/agent_sdk/issues
Keywords: ai,agent,llm,swarm,middleware,framework,rag
Classifier: Development Status :: 4 - Beta
Classifier: Intended Audience :: Developers
Classifier: Programming Language :: Python :: 3
Classifier: Programming Language :: Python :: 3.9
Classifier: Programming Language :: Python :: 3.10
Classifier: Programming Language :: Python :: 3.11
Classifier: Programming Language :: Python :: 3.12
Classifier: Programming Language :: Python :: 3.13
Classifier: Topic :: Scientific/Engineering :: Artificial Intelligence
Requires-Python: >=3.9
License-File: LICENSE
Requires-Dist: requests>=2.28
Requires-Dist: httpx>=0.24
Requires-Dist: colorama
Requires-Dist: python-dotenv
Requires-Dist: markdownify
Provides-Extra: openai
Requires-Dist: openai>=1.12.0; extra == "openai"
Provides-Extra: anthropic
Requires-Dist: anthropic>=0.18.0; extra == "anthropic"
Provides-Extra: gemini
Requires-Dist: google-generativeai>=0.4.0; extra == "gemini"
Provides-Extra: ollama
Requires-Dist: ollama; extra == "ollama"
Provides-Extra: rag
Requires-Dist: chromadb>=0.4.0; extra == "rag"
Provides-Extra: tools
Requires-Dist: duckduckgo-search>=5.0.0; extra == "tools"
Requires-Dist: wikipedia; extra == "tools"
Provides-Extra: docs
Requires-Dist: mkdocs>=1.4.0; extra == "docs"
Requires-Dist: mkdocs-material>=9.0.0; extra == "docs"
Provides-Extra: dev
Requires-Dist: pytest; extra == "dev"
Requires-Dist: build; extra == "dev"
Requires-Dist: agent-sdk-core[all,docs]; extra == "dev"
Provides-Extra: all
Requires-Dist: openai>=1.12.0; extra == "all"
Requires-Dist: anthropic>=0.18.0; extra == "all"
Requires-Dist: google-generativeai>=0.4.0; extra == "all"
Requires-Dist: ollama; extra == "all"
Requires-Dist: chromadb>=0.4.0; extra == "all"
Requires-Dist: duckduckgo-search>=5.0.0; extra == "all"
Requires-Dist: wikipedia; extra == "all"
Dynamic: license-file
